persistent_filters/__init__.py
persistent_filters/apps.py
persistent_filters/middleware.py
django_persistent_filters-1.2.dist-info/LICENSE
django_persistent_filters-1.2.dist-info/METADATA
django_persistent_filters-1.2.dist-info/WHEEL
django_persistent_filters-1.2.dist-info/top_level.txt
django_persistent_filters-1.2.dist-info/RECORD
