Metadata-Version: 2.1
Name: django-persistent-filters
Version: 1.2
Summary: Provide a django middleware that take care to persist the querystring in the browser cookies or in the Django session object.
Home-page: https://github.com/LorenzoProd/django-persistent-filters
Author: Lorenzo Prodon
Author-email: lorenzo.prodon@gmail.com
License: MIT
Classifier: Environment :: Web Environment
Classifier: Framework :: Django
Classifier: Framework :: Django :: 3.0
Classifier: Intended Audience :: Developers
Classifier: Operating System :: OS Independent
Classifier: Programming Language :: Python
Classifier: Programming Language :: Python :: 3
Classifier: Programming Language :: Python :: 3 :: Only
Classifier: Programming Language :: Python :: 3.6
Classifier: Programming Language :: Python :: 3.7
Classifier: Programming Language :: Python :: 3.8
Classifier: Programming Language :: Python :: 3.9
Classifier: Programming Language :: Python :: 3.10
Classifier: Topic :: Internet :: WWW/HTTP
Classifier: Topic :: Internet :: WWW/HTTP :: Dynamic Content
Requires-Python: >=3.6
License-File: LICENSE
Requires-Dist: Django>=2.2
Requires-Dist: urllib3>=2.5.0
